{
  "理财": [
    "余额宝",
    "基金",
    "黄金",
    "收益发放"
  ],
  "交通-打车": [
    "滴滴快车"
  ],
  "交通-公交": [
    "公交"
  ],
  "交通-地铁": [
    "地铁"
  ],
  "交通-火车": [
    "火车票"
  ],
  "交通-客运": [
    "车巴达"
  ],


  "餐饮-食堂": [
    "卡机",
    "食堂"
  ]
  "餐饮-外卖": [
    "外卖",
    "订单"
  ]

  "餐饮-快餐": [
    "肯德基",
    "麦当劳",
    "汉堡王",
    "老娘舅",
    "沙县",
    "烤肉拌饭",
    "吉野家",
    "食其家",
    "丸龟制面",
    "捞面",
  ]

  "餐饮-散食": [
    "麻辣烫",
    "杂粮煎饼",
    "鸡蛋",
    "炒饭",
    "冒菜",
    "土豆粉",
    "米线",
    "粥",
    "水饺",
    "馄饨",
  ]




  "餐饮-正餐": [

  ]
  
}
